README
setup.py
certdata/__init__.py
certdata/certdata.py
certdata.egg-info/PKG-INFO
certdata.egg-info/SOURCES.txt
certdata.egg-info/dependency_links.txt
certdata.egg-info/top_level.txt