Metadata-Version: 1.0
Name: certdata
Version: 0.1
Summary: certdata.txt parser
Home-page: https://github.com/AnimusPEXUS/certdata
Author: Alexey V Gorshkov
Author-email: animus@wayround.org
License: UNKNOWN
Platform: UNKNOWN
